concrete_lib-0.0.10-py3.9-nspkg.pth
concrete/lib/__init__.py
concrete/lib/file.py
concrete_lib-0.0.10.dist-info/LICENSE
concrete_lib-0.0.10.dist-info/METADATA
concrete_lib-0.0.10.dist-info/WHEEL
concrete_lib-0.0.10.dist-info/namespace_packages.txt
concrete_lib-0.0.10.dist-info/top_level.txt
concrete_lib-0.0.10.dist-info/RECORD
